<?xml version="1.0" encoding="UTF-8"?>
<odoo>
  <record id="account_config_debit_note_seq" model="ir.ui.view">
    <field name="name">account_config_settings.debit_note</field>
    <field name="model">account.config.settings</field>
    <field name="inherit_id" ref="account.view_account_config_settings"/>
    <field name="arch" type="xml">
      <group name="followup" position="after" >
        <group string="Sequencia da nota de débito" name="debit_note_seq">
            <group>
                <field name="debit_document_id" />
            </group>
            <group>
                <field name="debit_note_sequence_id" />
            </group>
        </group>
      </group>
    </field>
  </record>
</odoo>
